snmp_collector/__init__.py
snmp_collector/__main__.py
snmp_collector/event_loop.py
snmp_collector/collect/__init__.py
snmp_collector/collect/collector.py
snmp_collector/read_conf/__init__.py
snmp_collector/read_conf/read_configuration.py
snmp_collector/response/__init__.py
snmp_collector/response/response.py
snmp_collector/utility/__init__.py
snmp_collector/utility/utility.py
tests/__init__.py
tests/test.py
snmp_manager-1.1.5.dist-info/LICENSE
snmp_manager-1.1.5.dist-info/METADATA
snmp_manager-1.1.5.dist-info/WHEEL
snmp_manager-1.1.5.dist-info/top_level.txt
snmp_manager-1.1.5.dist-info/RECORD
