Metadata-Version: 2.1
Name: snmp-manager
Version: 1.1.5
Summary: SNMP collector through an asyncio loop
Home-page: https://github.com/agn-7/snmp-manager
Author: agn-7
Author-email: benyaminjmf@gmail.com
License: MIT
Download-URL: https://github.com/agn-7/snmp-manager/archive/1.1.5.zip
Keywords: snmp,snmp-collector,snmp-manager,asyncio,python3,python,docker,docker-compose
Platform: UNKNOWN
Classifier: Programming Language :: Python :: 3.6
Classifier: Programming Language :: Python :: 3.7
Classifier: Programming Language :: Python :: 3.8
Classifier: Programming Language :: Python :: 3.9
Requires-Python: >=3.6
